journal_sdk/__init__.py
journal_sdk/exceptions.py
journal_sdk/controllers/__init__.py
journal_sdk/controllers/attendance.py
journal_sdk/controllers/auth.py
journal_sdk/controllers/evaluation.py
journal_sdk/controllers/feedback.py
journal_sdk/controllers/grades.py
journal_sdk/controllers/homework.py
journal_sdk/controllers/leaderboard.py
journal_sdk/controllers/schedule.py
journal_sdk/controllers/user.py
journal_sdk/enums/endpoints.py
journal_sdk/enums/headers.py
journal_sdk/models/attendance.py
journal_sdk/models/auth.py
journal_sdk/models/evaluation.py
journal_sdk/models/feedback.py
journal_sdk/models/grades.py
journal_sdk/models/homework.py
journal_sdk/models/leaderboard.py
journal_sdk/models/schedule.py
journal_sdk/models/user.py
journal_sdk/rapid/client.py
journal_sdk/utils/app_key.py
top_journal_sdk_test-0.1.1.dist-info/METADATA
top_journal_sdk_test-0.1.1.dist-info/WHEEL
top_journal_sdk_test-0.1.1.dist-info/licenses/LICENSE
top_journal_sdk_test-0.1.1.dist-info/RECORD
