Metadata-Version: 2.4
Name: top_journal_sdk_test
Version: 0.1.1
Summary: Async-friendly SDK for ittopjournal API
Project-URL: Homepage, https://github.com/ITTopTools/top_journal_sdk
Project-URL: Issues, https://github.com/ITTopTools/top_journal_sdk/issues
Author-email: thegrayfoxxx <cool.afkshnik@gmail.com>
License-Expression: MIT
License-File: LICENSE
Classifier: Intended Audience :: Developers
Classifier: License :: OSI Approved :: MIT License
Classifier: Operating System :: OS Independent
Classifier: Programming Language :: Python
Classifier: Programming Language :: Python :: 3.13
Classifier: Programming Language :: Python :: 3.14
Classifier: Topic :: Internet
Classifier: Topic :: Internet :: WWW/HTTP
Classifier: Topic :: Internet :: WWW/HTTP :: Dynamic Content
Classifier: Topic :: Software Development
Classifier: Topic :: Software Development :: Libraries
Classifier: Topic :: Software Development :: Libraries :: Python Modules
Classifier: Topic :: Text Processing
Classifier: Topic :: Text Processing :: Markup :: HTML
Requires-Python: >=3.13
Requires-Dist: beautifulsoup4>=4.14.2
Requires-Dist: pydantic>=2.12.3
Requires-Dist: rapid-api-client>=0.9.0
Requires-Dist: twine>=6.2.0
